HyperRez/__init__.py
HyperRez/inference_realesrgan.py
HyperRez-2.0.dist-info/LICENSE
HyperRez-2.0.dist-info/METADATA
HyperRez-2.0.dist-info/WHEEL
HyperRez-2.0.dist-info/top_level.txt
HyperRez-2.0.dist-info/RECORD
