Metadata-Version: 2.1
Name: HyperRez
Version: 2.0
Summary: Sharpen Blurry Memories: Supercharge Your Images with HyperRez
Home-page: https://github.com/RauhanAhmed/HyperRez
Author: Rauhan Ahmed Siddiqui
Author-email: rauhaan.siddiqui@gamil.com
License: MIT
Keywords: computer vision,pytorch,image restoration,super-resolution,esrgan,real-esrgan,gfpgan,gradio,image enhancer,image quality enhancement,image upscaler,image quality upscaler
License-File: LICENSE
Requires-Dist: basicsr >=1.4.2
Requires-Dist: facexlib >=0.2.5
Requires-Dist: realesrgan
Requires-Dist: gradio
Requires-Dist: gfpgan >=1.3.5
Requires-Dist: numpy
Requires-Dist: opencv-python
Requires-Dist: Pillow
Requires-Dist: torch >=1.7
Requires-Dist: torchvision ==0.16.2
Requires-Dist: tqdm
